ccwriter/__about__.py
ccwriter/__init__.py
ccwriter-0.2.3.dist-info/METADATA
ccwriter-0.2.3.dist-info/WHEEL
ccwriter-0.2.3.dist-info/licenses/LICENSE
ccwriter-0.2.3.dist-info/RECORD
