Metadata-Version: 2.1
Name: ccwriter
Version: 0.2.3
Summary: Writer for CloudCompare .bin format
Project-URL: Source, https://github.com/mkrbac/ccwriter
Author-email: Marko Bausch <60338487+mrkbac@users.noreply.github.com>
License-Expression: MIT
License-File: LICENSE
Classifier: Development Status :: 4 - Beta
Classifier: Intended Audience :: Developers
Classifier: License :: OSI Approved :: MIT License
Classifier: Operating System :: OS Independent
Classifier: Programming Language :: Python :: 3.8
Classifier: Programming Language :: Python :: 3.9
Classifier: Programming Language :: Python :: 3.10
Classifier: Programming Language :: Python :: 3.11
Requires-Python: >=3.8
Requires-Dist: numpy>=1.22
